swagger_diff/__init__.py
swagger_diff/main.py
swagger_diff/model.py
swagger_diff/swagger_diff.py
swagger_diff/swagger_parser.py
swagger_diff/swaggercss.css
swagger_diff/template.html
swagger_diff-0.1.1.dist-info/entry_points.txt
swagger_diff-0.1.1.dist-info/WHEEL
swagger_diff-0.1.1.dist-info/METADATA
swagger_diff-0.1.1.dist-info/RECORD
