Metadata-Version: 2.1
Name: swagger-diff
Version: 0.1.1
Summary: 
License: MIT
Author: jun
Author-email: wandy1208@gmail.com
Requires-Python: >=3.7,<4.0
Classifier: License :: OSI Approved :: MIT License
Classifier: Programming Language :: Python :: 3
Classifier: Programming Language :: Python :: 3.7
Classifier: Programming Language :: Python :: 3.8
Requires-Dist: click (>=7.1.2,<8.0.0)
Requires-Dist: dictdiffer (>=0.8.1,<0.9.0)
Requires-Dist: jinja2 (>=2.11.2,<3.0.0)
Requires-Dist: pydantic (>=1.5.1,<2.0.0)
Requires-Dist: pyyaml (>=5.3.1,<6.0.0)
